bixi/__init__.py
bixi/constants.py
bixi/conversation.py
bixi/utils.py
bixi/api/__init__.py
bixi/api/completion.py
bixi/api/embedding.py
bixi/api/protocol.py
heliumos_bixi-0.1.6.dist-info/METADATA
heliumos_bixi-0.1.6.dist-info/WHEEL
heliumos_bixi-0.1.6.dist-info/top_level.txt
heliumos_bixi-0.1.6.dist-info/RECORD
